[{"id":3,"document_id":"uk1ryvyglvy2j006y6l4h10n","username":"Dime.Najdovski","email":"najdovski.dime@gmail.com","provider":"local","password":"$2a$10$GJysF0dMb0k8a7tp8HEhlef54HUtxpEpoE5DnvdI.5ViGgcKZJ1SW","reset_password_token":null,"confirmation_token":"0b6e31eddeccfc6731c5a9fe7fbc1118eaa1e706","confirmed":1,"blocked":0,"created_at":1747766868780,"updated_at":1748894857320,"published_at":1748894857312,"created_by_id":null,"updated_by_id":1,"locale":null,"first_name":"Dime","last_name":"Najdovski","gender":"Male","zip_code":"1000","country":"Macedonia","link_count":0,"input_count":120,"registration_order":1},
{"id":4,"document_id":"dav741zpd5jz80g1a1x7qk07","username":"test.test","email":"test@example.com","provider":"local","password":"$2a$10$aY/wajsFmbr24t00AAIN..2tJF75DsUQ9afvBiRWz1lzWA4KzZ1Z6","reset_password_token":null,"confirmation_token":"2b8a282495516df1c860630c89fde251c5b665da","confirmed":0,"blocked":0,"created_at":1748895193735,"updated_at":1748895193741,"published_at":1748895193735,"created_by_id":null,"updated_by_id":null,"locale":null,"first_name":"test","last_name":"test","gender":"male","zip_code":null,"country":"The Republic of North Macedonia","link_count":0,"input_count":0,"registration_order":null},
{"id":5,"document_id":"cavbif0pxkse8cs15v8x53gw","username":"test.test3","email":"test@tyest.com","provider":"local","password":"$2a$10$ihH3JZF9MoH7ymL8woROUu9Uuj9860gUFSs5oUWkJeTopQwpGyto.","reset_password_token":null,"confirmation_token":"bdff3ffe1866c67f3b9048d2e9bc6e1ffa63c3c1","confirmed":0,"blocked":0,"created_at":1748895882790,"updated_at":1748895882796,"published_at":1748895882791,"created_by_id":null,"updated_by_id":null,"locale":null,"first_name":"test","last_name":"test3","gender":"female","zip_code":"1000","country":"The Republic of North Macedonia","link_count":0,"input_count":0,"registration_order":null},
{"id":6,"document_id":"vrvrwio7bpjfokq8ms3cdwsr","username":"ghfjhgjf.jhghjg","email":"jhgjh@kyhu.com","provider":"local","password":"$2a$10$K0T5DRiaUbCxzR75XrPLBug2ZsDojymngmkxwa461IuA0loiuiPUi","reset_password_token":null,"confirmation_token":"a617e6fdeb919d3a8e56267c58e099a5e390d691","confirmed":0,"blocked":0,"created_at":1748895960966,"updated_at":1748895960971,"published_at":1748895960966,"created_by_id":null,"updated_by_id":null,"locale":null,"first_name":"ghfjhgjf","last_name":"jhghjg","gender":"male","zip_code":"1000","country":"Afghanistan","link_count":0,"input_count":0,"registration_order":null},
{"id":7,"document_id":"czrxh157knumu78qqzscj58a","username":"lkhkljh.kljhkjh","email":"kjhkjh@jhgjh.com","provider":"local","password":"$2a$10$KCpZv6dtLTKvyBGdZNn1GunJvb/eyzSeDJQwtgBwrnQlCFKp/jtLK","reset_password_token":null,"confirmation_token":"b59fd36aba745f5e673d08d57df7a6e2d425346a","confirmed":0,"blocked":0,"created_at":1748897987513,"updated_at":1748897987518,"published_at":1748897987514,"created_by_id":null,"updated_by_id":null,"locale":null,"first_name":"lkhkljh","last_name":"kljhkjh","gender":"male","zip_code":"1000","country":"Albania","link_count":0,"input_count":0,"registration_order":null},
{"id":8,"document_id":"btnqsvcrnlpyg9jbl28o2p1j","username":"asa.fdsfds","email":"fdsfds@jhgas.com","provider":"local","password":"$2a$10$UyO2vVLZhDhKRaeRFCC5COHzs3JAkjEJrenQ.qNXLUFsRbO.HC1RG","reset_password_token":null,"confirmation_token":"14f2110652d5aa3927198393a22e074ea57575d9","confirmed":0,"blocked":0,"created_at":1748898219879,"updated_at":1748898219884,"published_at":1748898219879,"created_by_id":null,"updated_by_id":null,"locale":null,"first_name":"asa","last_name":"fdsfds","gender":"female","zip_code":"1000","country":"Afghanistan","link_count":0,"input_count":0,"registration_order":null},
{"id":9,"document_id":"eqx6yg4zfrkavap0tpfuvf6d","username":"kuhkjkh.kjhkjh","email":"kjhkjh@kjghkj.com","provider":"local","password":"$2a$10$j7XCJKWnaYDwvmE0A.dXiO7gn347oUYYhxgq3lfHQaDfLReOYfkF2","reset_password_token":null,"confirmation_token":"5e30f995d5b74e25f8445d8c022475b68c7ddd95","confirmed":0,"blocked":0,"created_at":1748898810183,"updated_at":1748898810189,"published_at":1748898810184,"created_by_id":null,"updated_by_id":null,"locale":null,"first_name":"kuhkjkh","last_name":"kjhkjh","gender":"male","zip_code":"2121","country":"Afghanistan","link_count":0,"input_count":0,"registration_order":null},
{"id":10,"document_id":"aykx0oxl3x1dytuqcdju04u3","username":"jhjkhk.kjhkjh","email":"kjhkjh@hgj.com","provider":"local","password":"$2a$10$bIQbbaNeq3HrSzvk..Dl..LHFbwehVayqZ.ZoNds7FPNqt0JuJ7HG","reset_password_token":null,"confirmation_token":"a5b5bb412e4f5175a9460d7c0d10ff8c01dd309a","confirmed":0,"blocked":0,"created_at":1748898984571,"updated_at":1748898984577,"published_at":1748898984571,"created_by_id":null,"updated_by_id":null,"locale":null,"first_name":"jhjkhk","last_name":"kjhkjh","gender":"male","zip_code":"1000","country":"Albania","link_count":0,"input_count":0,"registration_order":null},
{"id":11,"document_id":"lkib790bh5q11fg9txggsjx5","username":"hjghjghjg.jhgjhg","email":"jhgjhg@jhgjh.com","provider":"local","password":"$2a$10$nfJlsyyqmk9nTAAxd8rOEesYcJEJckkgkaF86nxbb2pCi/pYeCEzi","reset_password_token":null,"confirmation_token":"c49eabf21c750bf5affe70f2d77ebda99b19684c","confirmed":0,"blocked":0,"created_at":1748899887733,"updated_at":1748899887738,"published_at":1748899887734,"created_by_id":null,"updated_by_id":null,"locale":null,"first_name":"hjghjghjg","last_name":"jhgjhg","gender":"male","zip_code":"1000","country":"Albania","link_count":0,"input_count":0,"registration_order":null}]
